tutorial4/fsm.sv
`timescale 1ns / 1ps
module fsm (
    input logic clk,
    input logic reset,
    input logic up,
    input logic down,
    output logic [7:0] count
);

logic pressed;
always_ff @( posedge clk ) begin 
    if (reset == 1'b1) begin
        count <= 8'b0;
        pressed <= 1'b0;
    end else begin
        if (up && !pressed) begin
            count <= count + 1'b1;
            pressed <= 1'b1;
        end else if (down && !pressed) begin
            count <= count - 1'b1;
        end else if (!down && !up) begin
            pressed <= 1'b0;
        end
    end
end
endmodule

tutorial4/fsm_tb.sv
module test;

logic u,d,clk,reset;
logic [7:0] count;
// generate clock
	always     // no sensitivity list, so it always executes
	begin
		clk = 1; #5; clk = 0; #5;
	end

/* oppure
logic clk=0;
always #10 clk = ~clk;
*/


initial begin
	$dumpfile("test.vcd");
	$dumpvars(0,test);
	reset = 1; #27; reset = 0;
	u = 0; d = 0; #10;
	u = 1; d = 0; #10;
	u = 0; d = 0; #10;
	u = 1; d = 0; #10;
	u = 0; d = 0; #10;
	u = 0; d = 1; #10;
	u = 0; d = 0; #10;

	# 10000 ;
	$finish;
end


      fsm fsm_inst(clk,reset,u,d,count);

      initial
	      $monitor("At time %t, u=%d  d= %d, count =%d" ,$time, u, d,count);
	   
endmodule // test

tutorial4/test.vcd
$date
	Sat Dec  2 09:15:17 2023
$end
$version
	Icarus Verilog
$end
$timescale
	1ps
$end
$scope module test $end
$var wire 8 ! count [7:0] $end
$var reg 1 " clk $end
$var reg 1 # d $end
$var reg 1 $ reset $end
$var reg 1 % u $end
$scope module fsm_inst $end
$var wire 1 " clk $end
$var wire 1 # down $end
$var wire 1 $ reset $end
$var wire 1 % up $end
$var reg 8 & count [7:0] $end
$var reg 1 ' pressed $end
$scope begin blockName $end
$upscope $end
$upscope $end
$upscope $end
$enddefinitions $end
$comment Show the parameter values. $end
$dumpall
$end
#0
$dumpvars
0'
b0 &
x%
1$
x#
1"
b0 !
$end
#5000
0"
#10000
1"
#15000
0"
#20000
1"
#25000
0"
#27000
0#
0%
0$
#30000
1"
#35000
0"
#37000
1%
#40000
1'
b1 !
b1 &
1"
#45000
0"
#47000
0%
#50000
0'
1"
#55000
0"
#57000
1%
#60000
1'
b10 !
b10 &
1"
#65000
0"
#67000
0%
#70000
0'
1"
#75000
0"
#77000
1#
#80000
b1 !
b1 &
1"
#85000
0"
#87000
0#
